mergetblib/__init__.py
mergetblib/grpc_client.py
mergetblib/identity.py
mergetblib/materialize.py
mergetblib/mergetb.py
mergetblib/model.py
mergetblib/realize.py
mergetblib/types.py
mergetblib/workspace.py
mergetblib/xdc.py
tests/__init__.py
tests/test_identity.py
tests/test_user.py
tests/test_workflow.py
tests/test_common/__init__.py
mergetblib-1.0.2.dist-info/LICENSE.md
mergetblib-1.0.2.dist-info/METADATA
mergetblib-1.0.2.dist-info/WHEEL
mergetblib-1.0.2.dist-info/top_level.txt
mergetblib-1.0.2.dist-info/RECORD
