Metadata-Version: 2.1
Name: mergetblib
Version: 1.0.2
Summary: ('MergeTB Python client library',)
Home-page: https://gitlab.com/mergetb/portal/python-client
Author: Brian Kocoloski
Author-email: bkocolos@isi.edu
License: MIT
Classifier: Programming Language :: Python :: 3
Classifier: License :: OSI Approved :: MIT License
Classifier: Operating System :: OS Independent
Classifier: Intended Audience :: Developers
Classifier: Intended Audience :: End Users/Desktop
Classifier: Development Status :: 4 - Beta
Requires-Python: >=3
License-File: LICENSE.md
Requires-Dist: betterproto>=2.0.0b6
Requires-Dist: grpclib>=0.4.7
Requires-Dist: paramiko>=3.4.0
Requires-Dist: validators>=0.33.0
Requires-Dist: timeout-timer>=0.2.0
Requires-Dist: pwinput>=1.0.3
Requires-Dist: mergetbapi
